README.md
guldlib.py
setup.py
guldlib.egg-info/PKG-INFO
guldlib.egg-info/SOURCES.txt
guldlib.egg-info/dependency_links.txt
guldlib.egg-info/top_level.txt